ssnipbox/__init__.py
ssnipbox/questions.py
ssnipbox-1.1.0.dist-info/METADATA
ssnipbox-1.1.0.dist-info/WHEEL
ssnipbox-1.1.0.dist-info/top_level.txt
ssnipbox-1.1.0.dist-info/RECORD
