Metadata-Version: 2.4
Name: ssnipbox
Version: 1.1.0
Summary: A package providing code snippets for questions Q1 to Q13.
Author-email: Learner <learningtrading63@gmail.com>
Requires-Python: >=3.8
